sehgsigizseigseigisegise/__init__.py
sehgsigizseigseigisegise-1.0.0.dist-info/METADATA
sehgsigizseigseigisegise-1.0.0.dist-info/WHEEL
sehgsigizseigseigisegise-1.0.0.dist-info/top_level.txt
sehgsigizseigseigisegise-1.0.0.dist-info/RECORD
